[
  {
    "author": "TryKatChup",
    "task": "Build macOS e iOS",
    "url": "https://github.com/TryKatChup"
  },
  {
    "author": "Federicoand98",
    "task": "Build macOS e iOS",
    "url": "https://github.com/Federicoand98"
  },
  {
    "author": "lollofred",
    "task": "Spiegazione domande",
    "url": "https://github.com/lollofred"
  },
  {
    "author": "filippoveronesi",
    "task": "Spiegazione domande",
    "url": "https://github.com/filippoveronesi"
  },
  {
    "author": "RedDuality",
    "task": "Nuove domande",
    "url": "https://github.com/RedDuality"
  },
  {
    "author": "jchergu",
    "task": "Calcolo voto finale e nuove domande",
    "url": "https://github.com/jchergu"
  },
  {
    "author": "VaiTon",
    "task": "Calcolo voto finale e piccolo refactor",
    "url": "https://github.com/VaiTon"
  }
]
